{
  "feature_schema": {
    "feature_count": 77,
    "feature_names": [
      "X1",
      "X10",
      "X11",
      "X12",
      "X13",
      "X14",
      "X15",
      "X16",
      "X17",
      "X18",
      "X19",
      "X2",
      "X20",
      "X21",
      "X22",
      "X23",
      "X24",
      "X25",
      "X26",
      "X27",
      "X28",
      "X29",
      "X3",
      "X30",
      "X31",
      "X32",
      "X33",
      "X34",
      "X35",
      "X36",
      "X37",
      "X4",
      "X5",
      "X6",
      "X7",
      "X8",
      "X9",
      "band_offset_db_1",
      "band_offset_db_2",
      "band_offset_db_3",
      "band_offset_db_4",
      "compress_ratio",
      "compress_ratio_high",
      "env_overrun_max",
      "env_overrun_mean",
      "env_overrun_rate",
      "freq_shift_score",
      "global_offset_db",
      "high_low_energy_ratio",
      "mod_[RF板][Mixer1]",
      "mod_[RF板][Mixer2]",
      "mod_[RF板][RF] 低频通路固定滤波/抑制网络",
      "mod_[RF板][RF] 步进衰减器/ATT",
      "mod_[RF板][RF] 输入连接/匹配/保护",
      "mod_[RF板][YTF]",
      "mod_[数字中频板][ADC]",
      "mod_[数字中频板][RBW]",
      "mod_[数字中频板][VBW]",
      "mod_[数字中频板][检波/对数]",
      "mod_[时钟板][参考分配]",
      "mod_[时钟板][参考域] 10MHz基准",
      "mod_[校准链路][校准源]",
      "mod_[校准链路][校准表/存储]",
      "mod_[校准链路][校准路径开关/耦合]",
      "mod_中频放大器",
      "mod_前置放大器",
      "mod_数字放大器",
      "mod_本振源(谐波发生器)",
      "offset_db",
      "offset_slope",
      "ripple_hp",
      "shape_rmse",
      "switch_step_mean_abs",
      "switch_step_std",
      "tail_asym",
      "viol_energy_aligned",
      "viol_rate_aligned"
    ]
  },
  "schema_diff": {
    "prev_count": 0,
    "curr_count": 77,
    "missing_from_prev": [],
    "added_since_prev": [
      "X1",
      "X10",
      "X11",
      "X12",
      "X13",
      "X14",
      "X15",
      "X16",
      "X17",
      "X18",
      "X19",
      "X2",
      "X20",
      "X21",
      "X22",
      "X23",
      "X24",
      "X25",
      "X26",
      "X27",
      "X28",
      "X29",
      "X3",
      "X30",
      "X31",
      "X32",
      "X33",
      "X34",
      "X35",
      "X36",
      "X37",
      "X4",
      "X5",
      "X6",
      "X7",
      "X8",
      "X9",
      "band_offset_db_1",
      "band_offset_db_2",
      "band_offset_db_3",
      "band_offset_db_4",
      "compress_ratio",
      "compress_ratio_high",
      "env_overrun_max",
      "env_overrun_mean",
      "env_overrun_rate",
      "freq_shift_score",
      "global_offset_db",
      "high_low_energy_ratio",
      "mod_[RF板][Mixer1]",
      "mod_[RF板][Mixer2]",
      "mod_[RF板][RF] 低频通路固定滤波/抑制网络",
      "mod_[RF板][RF] 步进衰减器/ATT",
      "mod_[RF板][RF] 输入连接/匹配/保护",
      "mod_[RF板][YTF]",
      "mod_[数字中频板][ADC]",
      "mod_[数字中频板][RBW]",
      "mod_[数字中频板][VBW]",
      "mod_[数字中频板][检波/对数]",
      "mod_[时钟板][参考分配]",
      "mod_[时钟板][参考域] 10MHz基准",
      "mod_[校准链路][校准源]",
      "mod_[校准链路][校准表/存储]",
      "mod_[校准链路][校准路径开关/耦合]",
      "mod_中频放大器",
      "mod_前置放大器",
      "mod_数字放大器",
      "mod_本振源(谐波发生器)",
      "offset_db",
      "offset_slope",
      "ripple_hp",
      "shape_rmse",
      "switch_step_mean_abs",
      "switch_step_std",
      "tail_asym",
      "viol_energy_aligned",
      "viol_rate_aligned"
    ]
  },
  "baseline_normal_stats": {
    "X1": {
      "mean": -9.94680887957317,
      "std": 0.045197849403223765
    },
    "X2": {
      "mean": 0.0007745784689173089,
      "std": 0.0004814415975746849
    },
    "X3": {
      "mean": 0.00023685351570470052,
      "std": 0.00013081790927359482
    },
    "X4": {
      "mean": 0.03035732976713546,
      "std": 0.004912040733487431
    },
    "X5": {
      "mean": 0.27853944883296944,
      "std": 0.038656872249777034
    },
    "X6": {
      "mean": 0.0011525828213303094,
      "std": 0.0005750395750959169
    },
    "X7": {
      "mean": 0.08687499999999976,
      "std": 0.013564084008881587
    },
    "X8": {
      "mean": 0.026433879573170692,
      "std": 0.005291892487571193
    },
    "X9": {
      "mean": 0.0009456956147580484,
      "std": 0.00030891557322728676
    },
    "X10": {
      "mean": 0.01670801936562413,
      "std": 0.006367831510332792
    },
    "X11": {
      "mean": 0.0011432926829268292,
      "std": 0.007730552517245564
    },
    "X12": {
      "mean": 0.0019314217119944799,
      "std": 0.007677802418961262
    },
    "X13": {
      "mean": 0.2018880156186028,
      "std": 0.1163379367840786
    },
    "X14": {
      "mean": 0.0098567708333333,
      "std": 0.011003446716874777
    },
    "X15": {
      "mean": 0.009641907400696174,
      "std": 0.004391722387002499
    },
    "X16": {
      "mean": -8.609646108576454,
      "std": 68.30943673414812
    },
    "X17": {
      "mean": 0.0,
      "std": 0.0
    },
    "X18": {
      "mean": 0.0,
      "std": 0.0
    },
    "X19": {
      "mean": -6.189429211181138e-05,
      "std": 0.00012412201128121162
    },
    "X20": {
      "mean": 0.25232423271708965,
      "std": 0.9763412472692526
    },
    "X21": {
      "mean": 5.15625,
      "std": 2.4058441216130357
    },
    "X22": {
      "mean": 0.04172443340812679,
      "std": 0.007927447238403875
    },
    "X23": {
      "mean": 0.0002163345560213366,
      "std": 0.0006818706389248582
    },
    "X24": {
      "mean": 0.04823831782184003,
      "std": 0.007383045147865359
    },
    "X25": {
      "mean": 0.00020886493137409976,
      "std": 0.0006232778673296267
    },
    "X26": {
      "mean": 0.0004915218632859582,
      "std": 0.0004156092102021696
    },
    "X27": {
      "mean": 0.00012715242773007212,
      "std": 8.995737624471356e-05
    },
    "X28": {
      "mean": -0.0010778424597112394,
      "std": 0.30773109490908873
    },
    "X29": {
      "mean": 0.4001786121592046,
      "std": 0.6367560315581585
    },
    "X30": {
      "mean": 0.007911987694969973,
      "std": 0.013932667720272364
    },
    "X31": {
      "mean": 0.006862334949106487,
      "std": 0.008744195445856334
    },
    "X32": {
      "mean": -1.9470261401914812,
      "std": 0.706044514593949
    },
    "X33": {
      "mean": 0.5486704259863868,
      "std": 0.06968925383091866
    },
    "X34": {
      "mean": 0.018129069238637642,
      "std": 0.0050764385257894415
    },
    "X35": {
      "mean": 0.00032074876054958483,
      "std": 6.926771374799261e-06
    },
    "X36": {
      "mean": 0.8103305126894131,
      "std": 0.05804814496322186
    },
    "X37": {
      "mean": 0.030357329767135458,
      "std": 0.004912040733487431
    },
    "offset_db": {
      "mean": -0.013632812500000133,
      "std": 0.04573014358948415
    },
    "viol_rate_aligned": {
      "mean": 0.0011432926829268292,
      "std": 0.007730552517245564
    },
    "viol_energy_aligned": {
      "mean": 0.2018880156186028,
      "std": 0.1163379367840786
    },
    "global_offset_db": {
      "mean": 1.3877787807814457e-17,
      "std": 1.1015152586160387e-16
    },
    "shape_rmse": {
      "mean": 0.011761630272094682,
      "std": 0.008831682136710003
    },
    "ripple_hp": {
      "mean": 0.005519378660492314,
      "std": 0.00041474531782179324
    },
    "tail_asym": {
      "mean": -0.00023632812499978017,
      "std": 0.007018708161171261
    },
    "compress_ratio": {
      "mean": 0.1548971036585366,
      "std": 0.04251736847850493
    },
    "compress_ratio_high": {
      "mean": 0.1454449152542373,
      "std": 0.049584305990941074
    },
    "freq_shift_score": {
      "mean": 0.0666477415868317,
      "std": 0.11530861102181826
    },
    "offset_slope": {
      "mean": 0.000272946571194225,
      "std": 0.004366626782869964
    },
    "high_low_energy_ratio": {
      "mean": 0.35918206089001337,
      "std": 0.3703624708205983
    },
    "band_offset_db_1": {
      "mean": -0.00023437499999989786,
      "std": 0.02794462559436745
    },
    "band_offset_db_2": {
      "mean": -0.0007031250000000822,
      "std": 0.011247558328782763
    },
    "band_offset_db_3": {
      "mean": 2.7755575615628914e-16,
      "std": 0.006285057925349294
    },
    "band_offset_db_4": {
      "mean": 0.0004687500000002953,
      "std": 0.010098392895034978
    }
  },
  "sim_normal_stats": {
    "X1": {
      "mean": 9.931649446341464,
      "std": 0.01786293704053949
    },
    "X10": {
      "mean": 0.02282533953793986,
      "std": 0.009449126680678837
    },
    "X11": {
      "mean": 0.04680487804878049,
      "std": 0.04213261265783754
    },
    "X12": {
      "mean": 0.04935712194880306,
      "std": 0.027738769191707296
    },
    "X13": {
      "mean": 0.766355006327436,
      "std": 0.4873789394966693
    },
    "X14": {
      "mean": 0.03425492002706942,
      "std": 0.008768905451100416
    },
    "X15": {
      "mean": 0.04325501750379799,
      "std": 0.010321405659633218
    },
    "X16": {
      "mean": -8.21309186612565,
      "std": 59.669537508676044
    },
    "X17": {
      "mean": 0.0,
      "std": 0.0
    },
    "X18": {
      "mean": 0.0,
      "std": 0.0
    },
    "X19": {
      "mean": -5.673732394099527e-05,
      "std": 0.0002859495295276714
    },
    "X2": {
      "mean": 0.002911775175945507,
      "std": 0.0008801652012375132
    },
    "X20": {
      "mean": 0.08973306398978007,
      "std": 0.5421921300380386
    },
    "X21": {
      "mean": 4.99,
      "std": 4.446335569882238
    },
    "X22": {
      "mean": 0.04330971428354844,
      "std": 0.010696546762025427
    },
    "X23": {
      "mean": 0.0022170893661657576,
      "std": 0.0007393451874720794
    },
    "X24": {
      "mean": 0.3304804554807327,
      "std": 0.03598525201014681
    },
    "X25": {
      "mean": 0.0021830418924371113,
      "std": 0.0006884144299721998
    },
    "X26": {
      "mean": 0.0007875096714548248,
      "std": 0.0006190124097543554
    },
    "X27": {
      "mean": 0.0005398350732162196,
      "std": 0.0003150489027328388
    },
    "X28": {
      "mean": -0.04492298499487478,
      "std": 0.15425241574863788
    },
    "X29": {
      "mean": 0.21087652285127895,
      "std": 0.7585364471291742
    },
    "X3": {
      "mean": 1.0390553745928351e-11,
      "std": 7.409115745301886e-12
    },
    "X30": {
      "mean": 0.06457543285982091,
      "std": 0.01367151019162455
    },
    "X31": {
      "mean": 0.02037263445541844,
      "std": 0.007523964160078215
    },
    "X32": {
      "mean": -3.303290943168427,
      "std": 0.35341485970399295
    },
    "X33": {
      "mean": 0.4777095588824863,
      "std": 0.06504994062438003
    },
    "X34": {
      "mean": 0.0277554177344276,
      "std": 0.005982229039592478
    },
    "X35": {
      "mean": 0.0006836979553578696,
      "std": 6.9527197951676e-05
    },
    "X36": {
      "mean": 0.882482430614287,
      "std": 0.03125084257907663
    },
    "X37": {
      "mean": 0.053409951032385675,
      "std": 0.007691053677076466
    },
    "X4": {
      "mean": 0.0,
      "std": 0.0
    },
    "X5": {
      "mean": 0.03268982310778868,
      "std": 0.004476670368751702
    },
    "X6": {
      "mean": 0.003163770830542903,
      "std": 0.0009513284862119797
    },
    "X7": {
      "mean": 0.132898288975304,
      "std": 0.02293779196506973
    },
    "X8": {
      "mean": 0.044158588809634136,
      "std": 0.0064029983933608
    },
    "X9": {
      "mean": 0.002911774216132312,
      "std": 0.0008801730002265353
    },
    "band_offset_db_1": {
      "mean": 0.001293843731942328,
      "std": 0.040112977261011644
    },
    "band_offset_db_2": {
      "mean": 0.0023300280844073917,
      "std": 0.01258211820476419
    },
    "band_offset_db_3": {
      "mean": -0.0015813374986570672,
      "std": 0.021969723204031295
    },
    "band_offset_db_4": {
      "mean": -0.0018977035395983143,
      "std": 0.015537308121052144
    },
    "compress_ratio": {
      "mean": 0.19999999999999996,
      "std": 5.551115123125783e-17
    },
    "compress_ratio_high": {
      "mean": 0.19999999999999996,
      "std": 5.551115123125783e-17
    },
    "env_overrun_max": {
      "mean": 0.04935712194880306,
      "std": 0.027738769191707296
    },
    "env_overrun_mean": {
      "mean": 0.001096966575910662,
      "std": 0.0014711215434154669
    },
    "env_overrun_rate": {
      "mean": 0.04680487804878049,
      "std": 0.04213261265783754
    },
    "freq_shift_score": {
      "mean": 0.44171629718198735,
      "std": 0.12453467275676261
    },
    "global_offset_db": {
      "mean": -8.881784197001253e-18,
      "std": 1.5358040586646547e-16
    },
    "high_low_energy_ratio": {
      "mean": 2.484111348252073,
      "std": 3.3602059231296364
    },
    "mod_[RF板][Mixer1]": {
      "mean": 0.018101187450187593,
      "std": 0.019209572602338295
    },
    "mod_[RF板][Mixer2]": {
      "mean": 0.0,
      "std": 0.0
    },
    "mod_[RF板][RF] 低频通路固定滤波/抑制网络": {
      "mean": 0.017804446672315673,
      "std": 0.018894661576070455
    },
    "mod_[RF板][RF] 步进衰减器/ATT": {
      "mean": 0.0,
      "std": 0.0
    },
    "mod_[RF板][RF] 输入连接/匹配/保护": {
      "mean": 0.32153357322531645,
      "std": 0.01260368705098363
    },
    "mod_[RF板][YTF]": {
      "mean": 0.0,
      "std": 0.0
    },
    "mod_[数字中频板][ADC]": {
      "mean": 0.07399139695248849,
      "std": 0.007673306946429907
    },
    "mod_[数字中频板][RBW]": {
      "mean": 0.06829975103306628,
      "std": 0.007083052565935295
    },
    "mod_[数字中频板][VBW]": {
      "mean": 0.05691645919422192,
      "std": 0.005902543804946081
    },
    "mod_[数字中频板][检波/对数]": {
      "mean": 0.07968304287191068,
      "std": 0.008263561326924513
    },
    "mod_[时钟板][参考分配]": {
      "mean": 0.014540298115724463,
      "std": 0.015430640287124202
    },
    "mod_[时钟板][参考域] 10MHz基准": {
      "mean": 0.014540298115724463,
      "std": 0.015430640287124202
    },
    "mod_[校准链路][校准源]": {
      "mean": 0.028369013113671477,
      "std": 0.0029420196719393806
    },
    "mod_[校准链路][校准表/存储]": {
      "mean": 0.021276759835253612,
      "std": 0.0022065147539545352
    },
    "mod_[校准链路][校准路径开关/耦合]": {
      "mean": 0.056738026227342954,
      "std": 0.005884039343878761
    },
    "mod_中频放大器": {
      "mean": 0.11952456430786601,
      "std": 0.012395341990386775
    },
    "mod_前置放大器": {
      "mean": 0.0,
      "std": 0.0
    },
    "mod_数字放大器": {
      "mean": 0.10244962654959944,
      "std": 0.010624578848902945
    },
    "mod_本振源(谐波发生器)": {
      "mean": 0.006231556335310486,
      "std": 0.006613131551624659
    },
    "offset_db": {
      "mean": 0.002999999999999714,
      "std": 0.016896745248715664
    },
    "offset_slope": {
      "mean": -0.0003929280596006854,
      "std": 0.00458772433168828
    },
    "ripple_hp": {
      "mean": 0.019400485237679198,
      "std": 0.001700814415827883
    },
    "shape_rmse": {
      "mean": 0.046517567804312085,
      "std": 0.007294193014788269
    },
    "switch_step_mean_abs": {
      "mean": 0.0,
      "std": 0.0
    },
    "switch_step_std": {
      "mean": 0.0,
      "std": 0.0
    },
    "tail_asym": {
      "mean": -0.009744108898420603,
      "std": 0.02650092510093135
    },
    "viol_energy_aligned": {
      "mean": 0.001096966575910662,
      "std": 0.0014711215434154669
    },
    "viol_rate_aligned": {
      "mean": 0.04680487804878049,
      "std": 0.04213261265783754
    }
  },
  "separation": [
    {
      "feature": "X1",
      "class": "正常",
      "mean": 9.931649446341464,
      "std": 0.01786293704053949,
      "fisher_score": 0.3902928781446688,
      "auc_ovr": 0.6328333333333334,
      "n": 100
    },
    {
      "feature": "X1",
      "class": "幅度失准",
      "mean": 9.933684509756098,
      "std": 0.008105960317118374,
      "fisher_score": 0.49170493550624267,
      "auc_ovr": 0.66945,
      "n": 100
    },
    {
      "feature": "X1",
      "class": "频率失准",
      "mean": 9.93307312317073,
      "std": 1.1570458958695992e-06,
      "fisher_score": 0.4751010519663785,
      "auc_ovr": 0.6977166666666667,
      "n": 100
    },
    {
      "feature": "X1",
      "class": "参考电平失准",
      "mean": 9.826672060975609,
      "std": 0.013708732555555395,
      "fisher_score": 35.54085045512745,
      "auc_ovr": 0.0,
      "n": 100
    },
    {
      "feature": "X10",
      "class": "正常",
      "mean": 0.02282533953793986,
      "std": 0.009449126680678837,
      "fisher_score": 0.02881343414046179,
      "auc_ovr": 0.6258333333333335,
      "n": 100
    },
    {
      "feature": "X10",
      "class": "幅度失准",
      "mean": 0.02865442721300149,
      "std": 0.0169420288090979,
      "fisher_score": 0.3190328750208012,
      "auc_ovr": 0.6570333333333334,
      "n": 100
    },
    {
      "feature": "X10",
      "class": "频率失准",
      "mean": 0.01592488562247215,
      "std": 0.0031260794890919062,
      "fisher_score": 0.2658581200848732,
      "auc_ovr": 0.3474666666666667,
      "n": 100
    },
    {
      "feature": "X10",
      "class": "参考电平失准",
      "mean": 0.016206187216111424,
      "std": 0.0037229074446322717,
      "fisher_score": 0.23116990218211667,
      "auc_ovr": 0.3696666666666667,
      "n": 100
    },
    {
      "feature": "X11",
      "class": "正常",
      "mean": 0.04680487804878049,
      "std": 0.04213261265783754,
      "fisher_score": 0.20277863687189882,
      "auc_ovr": 0.9065833333333333,
      "n": 100
    },
    {
      "feature": "X11",
      "class": "幅度失准",
      "mean": 0.044890243902439016,
      "std": 0.09066623244040495,
      "fisher_score": 0.09149842153326643,
      "auc_ovr": 0.58855,
      "n": 100
    },
    {
      "feature": "X11",
      "class": "频率失准",
      "mean": 0.0001097560975609756,
      "std": 0.0005201187344423445,
      "fisher_score": 0.2456628253415655,
      "auc_ovr": 0.26028333333333337,
      "n": 100
    },
    {
      "feature": "X11",
      "class": "参考电平失准",
      "mean": 0.00025609756097560977,
      "std": 0.0025481385584437827,
      "fisher_score": 0.24207994862034657,
      "auc_ovr": 0.24458333333333335,
      "n": 100
    },
    {
      "feature": "X12",
      "class": "正常",
      "mean": 0.04935712194880306,
      "std": 0.027738769191707296,
      "fisher_score": 1.4037027336274885,
      "auc_ovr": 0.9244666666666667,
      "n": 100
    },
    {
      "feature": "X12",
      "class": "幅度失准",
      "mean": 0.02268986908471117,
      "std": 0.032613577782949404,
      "fisher_score": 0.020166121288264442,
      "auc_ovr": 0.5725666666666667,
      "n": 100
    },
    {
      "feature": "X12",
      "class": "频率失准",
      "mean": 0.0002751382970802574,
      "std": 0.001422731663899284,
      "fisher_score": 0.5542191646966195,
      "auc_ovr": 0.2601333333333333,
      "n": 100
    },
    {
      "feature": "X12",
      "class": "参考电平失准",
      "mean": 7.116297322248499e-05,
      "std": 0.0007080626434352737,
      "fisher_score": 0.5693603676519028,
      "auc_ovr": 0.24283333333333335,
      "n": 100
    },
    {
      "feature": "X13",
      "class": "正常",
      "mean": 0.766355006327436,
      "std": 0.4873789394966693,
      "fisher_score": 0.0664063747072289,
      "auc_ovr": 0.6285333333333334,
      "n": 100
    },
    {
      "feature": "X13",
      "class": "幅度失准",
      "mean": 0.4516321542468249,
      "std": 0.6701377078830407,
      "fisher_score": 0.08730406150104185,
      "auc_ovr": 0.26789999999999997,
      "n": 100
    },
    {
      "feature": "X13",
      "class": "频率失准",
      "mean": 0.6940603842054276,
      "std": 0.3860433425711347,
      "fisher_score": 0.016628865156552104,
      "auc_ovr": 0.5963666666666667,
      "n": 100
    },
    {
      "feature": "X13",
      "class": "参考电平失准",
      "mean": 0.6039258814089277,
      "std": 0.41787083334758335,
      "fisher_score": 0.0023703726770765675,
      "auc_ovr": 0.5072,
      "n": 100
    },
    {
      "feature": "X14",
      "class": "正常",
      "mean": 0.03425492002706942,
      "std": 0.008768905451100416,
      "fisher_score": 0.6675731760252338,
      "auc_ovr": 0.8419333333333333,
      "n": 100
    },
    {
      "feature": "X14",
      "class": "幅度失准",
      "mean": 0.03534081079612516,
      "std": 0.019335910376439832,
      "fisher_score": 0.5250293545272431,
      "auc_ovr": 0.7741999999999999,
      "n": 100
    },
    {
      "feature": "X14",
      "class": "频率失准",
      "mean": 0.010294253424946487,
      "std": 0.005346493465379998,
      "fisher_score": 0.85862895806927,
      "auc_ovr": 0.18006666666666668,
      "n": 100
    },
    {
      "feature": "X14",
      "class": "参考电平失准",
      "mean": 0.010780104382329646,
      "std": 0.005410396642435169,
      "fisher_score": 0.7785307040284478,
      "auc_ovr": 0.2038,
      "n": 100
    },
    {
      "feature": "X15",
      "class": "正常",
      "mean": 0.04325501750379799,
      "std": 0.010321405659633218,
      "fisher_score": 1.3948751525531267,
      "auc_ovr": 0.9008,
      "n": 100
    },
    {
      "feature": "X15",
      "class": "幅度失准",
      "mean": 0.035451951615252504,
      "std": 0.017922763435241556,
      "fisher_score": 0.23446905624083864,
      "auc_ovr": 0.6998666666666666,
      "n": 100
    },
    {
      "feature": "X15",
      "class": "频率失准",
      "mean": 0.013772640351908626,
      "std": 0.006950667722934062,
      "fisher_score": 0.8317832665946253,
      "auc_ovr": 0.19079999999999997,
      "n": 100
    },
    {
      "feature": "X15",
      "class": "参考电平失准",
      "mean": 0.014347674254952618,
      "std": 0.007257488120315391,
      "fisher_score": 0.7400726778076753,
      "auc_ovr": 0.20853333333333335,
      "n": 100
    },
    {
      "feature": "X16",
      "class": "正常",
      "mean": -8.21309186612565,
      "std": 59.669537508676044,
      "fisher_score": 0.011201825516312502,
      "auc_ovr": 0.41866666666666663,
      "n": 100
    },
    {
      "feature": "X16",
      "class": "幅度失准",
      "mean": -4.311004880768833,
      "std": 40.12155577831638,
      "fisher_score": 0.0008824838800281949,
      "auc_ovr": 0.5990333333333333,
      "n": 100
    },
    {
      "feature": "X16",
      "class": "频率失准",
      "mean": 0.004005448380454461,
      "std": 0.1225215141496051,
      "fisher_score": 0.010063689950623646,
      "auc_ovr": 0.46486666666666676,
      "n": 100
    },
    {
      "feature": "X16",
      "class": "参考电平失准",
      "mean": 0.0015797858860659016,
      "std": 0.008309708813037883,
      "fisher_score": 0.010048134490119768,
      "auc_ovr": 0.5174333333333333,
      "n": 100
    },
    {
      "feature": "X17",
      "class": "正常",
      "mean": 0.0,
      "std": 0.0,
      "fisher_score": 9.74753874646186e-05,
      "auc_ovr": 0.49666666666666665,
      "n": 100
    },
    {
      "feature": "X17",
      "class": "幅度失准",
      "mean": -5.0000000000005595e-06,
      "std": 0.00011169153951844098,
      "fisher_score": 0.0018872197478678194,
      "auc_ovr": 0.4964833333333333,
      "n": 100
    },
    {
      "feature": "X17",
      "class": "频率失准",
      "mean": 9.999999999998898e-06,
      "std": 0.0002643860813280166,
      "fisher_score": 0.0018132701772565025,
      "auc_ovr": 0.5101833333333333,
      "n": 100
    },
    {
      "feature": "X17",
      "class": "参考电平失准",
      "mean": 0.0,
      "std": 0.0,
      "fisher_score": 9.74753874646186e-05,
      "auc_ovr": 0.49666666666666665,
      "n": 100
    },
    {
      "feature": "X18",
      "class": "正常",
      "mean": 0.0,
      "std": 0.0,
      "fisher_score": 0.0,
      "auc_ovr": 0.5,
      "n": 100
    },
    {
      "feature": "X18",
      "class": "幅度失准",
      "mean": 0.0,
      "std": 7.071067811865475e-05,
      "fisher_score": 0.0,
      "auc_ovr": 0.5,
      "n": 100
    },
    {
      "feature": "X18",
      "class": "频率失准",
      "mean": 0.0,
      "std": 0.0001414213562373095,
      "fisher_score": 0.0,
      "auc_ovr": 0.5,
      "n": 100
    },
    {
      "feature": "X18",
      "class": "参考电平失准",
      "mean": 0.0,
      "std": 0.0,
      "fisher_score": 0.0,
      "auc_ovr": 0.5,
      "n": 100
    },
    {
      "feature": "X19",
      "class": "正常",
      "mean": -5.673732394099527e-05,
      "std": 0.0002859495295276714,
      "fisher_score": 0.0045617308673537435,
      "auc_ovr": 0.5127666666666667,
      "n": 100
    },
    {
      "feature": "X19",
      "class": "幅度失准",
      "mean": -9.791688019906958e-05,
      "std": 0.00020673043351146316,
      "fisher_score": 0.01316232469822925,
      "auc_ovr": 0.46043333333333336,
      "n": 100
    },
    {
      "feature": "X19",
      "class": "频率失准",
      "mean": -8.08422576887926e-05,
      "std": 0.00012773091264530278,
      "fisher_score": 0.0015541036595242608,
      "auc_ovr": 0.49590000000000006,
      "n": 100
    },
    {
      "feature": "X19",
      "class": "参考电平失准",
      "mean": -5.7929553362347013e-05,
      "std": 0.00012147339863113543,
      "fisher_score": 0.006717806284563814,
      "auc_ovr": 0.5308999999999999,
      "n": 100
    },
    {
      "feature": "X2",
      "class": "正常",
      "mean": 0.002911775175945507,
      "std": 0.0008801652012375132,
      "fisher_score": 0.7380759213248069,
      "auc_ovr": 0.9098333333333334,
      "n": 100
    },
    {
      "feature": "X2",
      "class": "幅度失准",
      "mean": 0.0024904193708326413,
      "std": 0.001982922322743161,
      "fisher_score": 0.1339486669044613,
      "auc_ovr": 0.6772666666666666,
      "n": 100
    },
    {
      "feature": "X2",
      "class": "频率失准",
      "mean": 0.0010594755023329763,
      "std": 0.00024718957956221705,
      "fisher_score": 0.5209882619541818,
      "auc_ovr": 0.20263333333333333,
      "n": 100
    },
    {
      "feature": "X2",
      "class": "参考电平失准",
      "mean": 0.0010468593828130025,
      "std": 0.00019483600221164714,
      "fisher_score": 0.5430616400753311,
      "auc_ovr": 0.21026666666666666,
      "n": 100
    },
    {
      "feature": "X20",
      "class": "正常",
      "mean": 0.08973306398978007,
      "std": 0.5421921300380386,
      "fisher_score": 0.06702029514485966,
      "auc_ovr": 0.5798666666666666,
      "n": 100
    },
    {
      "feature": "X20",
      "class": "幅度失准",
      "mean": -0.30423828113125,
      "std": 0.32100997973918877,
      "fisher_score": 0.42626422249512125,
      "auc_ovr": 0.24503333333333335,
      "n": 100
    },
    {
      "feature": "X20",
      "class": "频率失准",
      "mean": 0.011096129895636934,
      "std": 0.3791370558856941,
      "fisher_score": 0.013042832090887977,
      "auc_ovr": 0.5640000000000001,
      "n": 100
    },
    {
      "feature": "X20",
      "class": "参考电平失准",
      "mean": 0.04528281543740424,
      "std": 0.35598960421418313,
      "fisher_score": 0.038064713509742346,
      "auc_ovr": 0.6110999999999999,
      "n": 100
    },
    {
      "feature": "X21",
      "class": "正常",
      "mean": 4.99,
      "std": 4.446335569882238,
      "fisher_score": 0.0704955616347354,
      "auc_ovr": 0.5670833333333334,
      "n": 100
    },
    {
      "feature": "X21",
      "class": "幅度失准",
      "mean": 2.38,
      "std": 2.2216210297888344,
      "fisher_score": 0.26729648694425595,
      "auc_ovr": 0.29188333333333333,
      "n": 100
    },
    {
      "feature": "X21",
      "class": "频率失准",
      "mean": 4.08,
      "std": 2.398666296090392,
      "fisher_score": 0.0015313485421942718,
      "auc_ovr": 0.56375,
      "n": 100
    },
    {
      "feature": "X21",
      "class": "参考电平失准",
      "mean": 4.37,
      "std": 2.9551818894951283,
      "fisher_score": 0.015266025281584954,
      "auc_ovr": 0.5772833333333334,
      "n": 100
    },
    {
      "feature": "X22",
      "class": "正常",
      "mean": 0.04330971428354844,
      "std": 0.010696546762025427,
      "fisher_score": 0.05768869562121263,
      "auc_ovr": 0.42423333333333335,
      "n": 100
    },
    {
      "feature": "X22",
      "class": "幅度失准",
      "mean": 0.05793515262469047,
      "std": 0.025133474909082538,
      "fisher_score": 0.3025676215446573,
      "auc_ovr": 0.6731333333333334,
      "n": 100
    },
    {
      "feature": "X22",
      "class": "频率失准",
      "mean": 0.043629587724635266,
      "std": 0.007198050235583289,
      "fisher_score": 0.05331110717598076,
      "auc_ovr": 0.4693666666666666,
      "n": 100
    },
    {
      "feature": "X22",
      "class": "参考电平失准",
      "mean": 0.04296430647649742,
      "std": 0.007862857232223242,
      "fisher_score": 0.07581517803742452,
      "auc_ovr": 0.4332666666666667,
      "n": 100
    },
    {
      "feature": "X23",
      "class": "正常",
      "mean": 0.0022170893661657576,
      "std": 0.0007393451874720794,
      "fisher_score": 0.5869430902320811,
      "auc_ovr": 0.8771666666666667,
      "n": 100
    },
    {
      "feature": "X23",
      "class": "幅度失准",
      "mean": 0.002196667013292121,
      "std": 0.0021413874846663425,
      "fisher_score": 0.29237021167603783,
      "auc_ovr": 0.7495333333333334,
      "n": 100
    },
    {
      "feature": "X23",
      "class": "频率失准",
      "mean": 0.00024926218644333043,
      "std": 0.0001788265163113687,
      "fisher_score": 0.6659976918739828,
      "auc_ovr": 0.16910000000000003,
      "n": 100
    },
    {
      "feature": "X23",
      "class": "参考电平失准",
      "mean": 0.00027121359796546097,
      "std": 0.00017120185519629575,
      "fisher_score": 0.6324141398050116,
      "auc_ovr": 0.20420000000000002,
      "n": 100
    },
    {
      "feature": "X24",
      "class": "正常",
      "mean": 0.3304804554807327,
      "std": 0.03598525201014681,
      "fisher_score": 2.921891135594578,
      "auc_ovr": 0.929,
      "n": 100
    },
    {
      "feature": "X24",
      "class": "幅度失准",
      "mean": 0.16516740036381983,
      "std": 0.20984284977138185,
      "fisher_score": 0.012129157705021846,
      "auc_ovr": 0.4735333333333334,
      "n": 100
    },
    {
      "feature": "X24",
      "class": "频率失准",
      "mean": 0.05808141643141455,
      "std": 0.06554341960426421,
      "fisher_score": 0.37320947761621287,
      "auc_ovr": 0.4182,
      "n": 100
    },
    {
      "feature": "X24",
      "class": "参考电平失准",
      "mean": 0.022797130449513356,
      "std": 0.013287902995855546,
      "fisher_score": 0.8940714982144009,
      "auc_ovr": 0.17926666666666669,
      "n": 100
    },
    {
      "feature": "X25",
      "class": "正常",
      "mean": 0.0021830418924371113,
      "std": 0.0006884144299721998,
      "fisher_score": 0.5583853202557304,
      "auc_ovr": 0.8759666666666667,
      "n": 100
    },
    {
      "feature": "X25",
      "class": "幅度失准",
      "mean": 0.0022021346794315463,
      "std": 0.002174071280709671,
      "fisher_score": 0.29494243428388617,
      "auc_ovr": 0.7504333333333333,
      "n": 100
    },
    {
      "feature": "X25",
      "class": "频率失准",
      "mean": 0.00025355148239074245,
      "std": 0.00017889526266409267,
      "fisher_score": 0.6494016178563997,
      "auc_ovr": 0.1717666666666667,
      "n": 100
    },
    {
      "feature": "X25",
      "class": "参考电平失准",
      "mean": 0.00027121359796546097,
      "std": 0.00017120185519629575,
      "fisher_score": 0.6228579581008267,
      "auc_ovr": 0.20183333333333336,
      "n": 100
    },
    {
      "feature": "X26",
      "class": "正常",
      "mean": 0.0007875096714548248,
      "std": 0.0006190124097543554,
      "fisher_score": 0.01705387851828164,
      "auc_ovr": 0.5493666666666667,
      "n": 100
    },
    {
      "feature": "X26",
      "class": "幅度失准",
      "mean": 0.001025587507024201,
      "std": 0.000732940566392917,
      "fisher_score": 0.23349771753558046,
      "auc_ovr": 0.6907666666666666,
      "n": 100
    },
    {
      "feature": "X26",
      "class": "频率失准",
      "mean": 0.0004259124295506126,
      "std": 0.0003530571669830352,
      "fisher_score": 0.2621699981150635,
      "auc_ovr": 0.3098666666666666,
      "n": 100
    },
    {
      "feature": "X26",
      "class": "参考电平失准",
      "mean": 0.0005767994335782894,
      "std": 0.0004177141442667704,
      "fisher_score": 0.04916579432105255,
      "auc_ovr": 0.45000000000000007,
      "n": 100
    },
    {
      "feature": "X27",
      "class": "正常",
      "mean": 0.0005398350732162196,
      "std": 0.0003150489027328388,
      "fisher_score": 0.7556631819148174,
      "auc_ovr": 0.8516666666666667,
      "n": 100
    },
    {
      "feature": "X27",
      "class": "幅度失准",
      "mean": 0.00026095666019201397,
      "std": 0.00035500889335878444,
      "fisher_score": 0.005146876234315195,
      "auc_ovr": 0.4218666666666668,
      "n": 100
    },
    {
      "feature": "X27",
      "class": "频率失准",
      "mean": 0.0001662666871926994,
      "std": 0.00011856069243974743,
      "fisher_score": 0.211205253988008,
      "auc_ovr": 0.3509666666666667,
      "n": 100
    },
    {
      "feature": "X27",
      "class": "参考电平失准",
      "mean": 0.00017284441535381703,
      "std": 0.00010946272727634942,
      "fisher_score": 0.18957961459981643,
      "auc_ovr": 0.37550000000000006,
      "n": 100
    },
    {
      "feature": "X28",
      "class": "正常",
      "mean": -0.04492298499487478,
      "std": 0.15425241574863788,
      "fisher_score": 0.4197134818182504,
      "auc_ovr": 0.7270333333333333,
      "n": 100
    },
    {
      "feature": "X28",
      "class": "幅度失准",
      "mean": -0.048287183653841555,
      "std": 0.22914264837321363,
      "fisher_score": 0.3307278247414882,
      "auc_ovr": 0.7378666666666667,
      "n": 100
    },
    {
      "feature": "X28",
      "class": "频率失准",
      "mean": -0.38364168166821583,
      "std": 0.20425343085747596,
      "fisher_score": 0.6631982441921055,
      "auc_ovr": 0.209,
      "n": 100
    },
    {
      "feature": "X28",
      "class": "参考电平失准",
      "mean": -0.29360675365634675,
      "std": 0.22653902817345634,
      "fisher_score": 0.1564412000549116,
      "auc_ovr": 0.32610000000000006,
      "n": 100
    },
    {
      "feature": "X29",
      "class": "正常",
      "mean": 0.21087652285127895,
      "std": 0.7585364471291742,
      "fisher_score": 0.018845916705365045,
      "auc_ovr": 0.5621666666666667,
      "n": 100
    },
    {
      "feature": "X29",
      "class": "幅度失准",
      "mean": 0.10977519535727573,
      "std": 0.811021138754625,
      "fisher_score": 0.0002436193264226236,
      "auc_ovr": 0.5328666666666666,
      "n": 100
    },
    {
      "feature": "X29",
      "class": "频率失准",
      "mean": 0.08726378676629473,
      "std": 1.1278372995320771,
      "fisher_score": 8.796317958132037e-05,
      "auc_ovr": 0.47783333333333333,
      "n": 100
    },
    {
      "feature": "X29",
      "class": "参考电平失准",
      "mean": -0.022117040851444128,
      "std": 0.19890319107132023,
      "fisher_score": 0.028480944852055035,
      "auc_ovr": 0.4271333333333333,
      "n": 100
    },
    {
      "feature": "X3",
      "class": "正常",
      "mean": 1.0390553745928351e-11,
      "std": 7.409115745301886e-12,
      "fisher_score": 1.9400151089134324e-14,
      "auc_ovr": 0.7033666666666667,
      "n": 100
    },
    {
      "feature": "X3",
      "class": "幅度失准",
      "mean": 1.214788273615636e-11,
      "std": 8.325611602140259e-12,
      "fisher_score": 4.5530990791527414e-14,
      "auc_ovr": 0.7656333333333334,
      "n": 100
    },
    {
      "feature": "X3",
      "class": "频率失准",
      "mean": 2.8188925081433166e-12,
      "std": 2.873968226241703e-12,
      "fisher_score": 3.2387345058772516e-14,
      "auc_ovr": 0.2521833333333333,
      "n": 100
    },
    {
      "feature": "X3",
      "class": "参考电平失准",
      "mean": 2.9912052117263848e-12,
      "std": 2.766501517718718e-12,
      "fisher_score": 2.982511814448763e-14,
      "auc_ovr": 0.2788166666666667,
      "n": 100
    },
    {
      "feature": "X30",
      "class": "正常",
      "mean": 0.06457543285982091,
      "std": 0.01367151019162455,
      "fisher_score": 1.3590320732155854,
      "auc_ovr": 0.8781666666666668,
      "n": 100
    },
    {
      "feature": "X30",
      "class": "幅度失准",
      "mean": 0.05695237945295517,
      "std": 0.036644639875106876,
      "fisher_score": 0.42170052939523356,
      "auc_ovr": 0.7598333333333332,
      "n": 100
    },
    {
      "feature": "X30",
      "class": "频率失准",
      "mean": 0.007602012017458196,
      "std": 0.005539219641073724,
      "fisher_score": 1.0962180172149443,
      "auc_ovr": 0.16563333333333335,
      "n": 100
    },
    {
      "feature": "X30",
      "class": "参考电平失准",
      "mean": 0.008615506743901172,
      "std": 0.006287150214963674,
      "fisher_score": 0.9898732977036977,
      "auc_ovr": 0.19636666666666666,
      "n": 100
    },
    {
      "feature": "X31",
      "class": "正常",
      "mean": 0.02037263445541844,
      "std": 0.007523964160078215,
      "fisher_score": 0.4579607981629527,
      "auc_ovr": 0.8520666666666666,
      "n": 100
    },
    {
      "feature": "X31",
      "class": "幅度失准",
      "mean": 0.018792830645960844,
      "std": 0.018194737157771777,
      "fisher_score": 0.1458631222372525,
      "auc_ovr": 0.5550666666666667,
      "n": 100
    },
    {
      "feature": "X31",
      "class": "频率失准",
      "mean": 0.006126627286135817,
      "std": 0.0030515333657601305,
      "fisher_score": 0.4823255866028342,
      "auc_ovr": 0.2622333333333333,
      "n": 100
    },
    {
      "feature": "X31",
      "class": "参考电平失准",
      "mean": 0.006990046551849145,
      "std": 0.0032570821255970676,
      "fisher_score": 0.3580260887616536,
      "auc_ovr": 0.33063333333333333,
      "n": 100
    },
    {
      "feature": "X32",
      "class": "正常",
      "mean": -3.303290943168427,
      "std": 0.35341485970399295,
      "fisher_score": 0.15818522847938762,
      "auc_ovr": 0.7280666666666668,
      "n": 100
    },
    {
      "feature": "X32",
      "class": "幅度失准",
      "mean": -9.887828095679417,
      "std": 9.54023625558825,
      "fisher_score": 0.43192600392105446,
      "auc_ovr": 0.32380000000000003,
      "n": 100
    },
    {
      "feature": "X32",
      "class": "频率失准",
      "mean": -3.2438816038755998,
      "std": 0.815877304549374,
      "fisher_score": 0.16729243184195552,
      "auc_ovr": 0.7000333333333333,
      "n": 100
    },
    {
      "feature": "X32",
      "class": "参考电平失准",
      "mean": -4.254209708797539,
      "std": 0.2933482375898632,
      "fisher_score": 0.037081261918551975,
      "auc_ovr": 0.24810000000000001,
      "n": 100
    },
    {
      "feature": "X33",
      "class": "正常",
      "mean": 0.4777095588824863,
      "std": 0.06504994062438003,
      "fisher_score": 0.02512426804059245,
      "auc_ovr": 0.41390000000000005,
      "n": 100
    },
    {
      "feature": "X33",
      "class": "幅度失准",
      "mean": 0.4713238419282988,
      "std": 0.25678688007946876,
      "fisher_score": 0.017896039142605968,
      "auc_ovr": 0.31773333333333326,
      "n": 100
    },
    {
      "feature": "X33",
      "class": "频率失准",
      "mean": 0.5108584597637639,
      "std": 0.05320950072174037,
      "fisher_score": 0.011011943743777047,
      "auc_ovr": 0.5765666666666667,
      "n": 100
    },
    {
      "feature": "X33",
      "class": "参考电平失准",
      "mean": 0.5311947767338616,
      "std": 0.04604835314346793,
      "fisher_score": 0.07422825874596005,
      "auc_ovr": 0.6918,
      "n": 100
    },
    {
      "feature": "X34",
      "class": "正常",
      "mean": 0.0277554177344276,
      "std": 0.005982229039592478,
      "fisher_score": 0.5364898023458541,
      "auc_ovr": 0.8431333333333333,
      "n": 100
    },
    {
      "feature": "X34",
      "class": "幅度失准",
      "mean": 0.026990756749412606,
      "std": 0.011568966100261424,
      "fisher_score": 0.24543042977620677,
      "auc_ovr": 0.6594333333333333,
      "n": 100
    },
    {
      "feature": "X34",
      "class": "频率失准",
      "mean": 0.016599234066367076,
      "std": 0.0023336013573847514,
      "fisher_score": 0.5935889484049434,
      "auc_ovr": 0.23963333333333334,
      "n": 100
    },
    {
      "feature": "X34",
      "class": "参考电平失准",
      "mean": 0.016850595176449337,
      "std": 0.002602931772305211,
      "fisher_score": 0.527777782391004,
      "auc_ovr": 0.2578,
      "n": 100
    },
    {
      "feature": "X35",
      "class": "正常",
      "mean": 0.0006836979553578696,
      "std": 6.9527197951676e-05,
      "fisher_score": 0.23840097387526132,
      "auc_ovr": 0.9329333333333334,
      "n": 100
    },
    {
      "feature": "X35",
      "class": "幅度失准",
      "mean": 0.0006786867447162251,
      "std": 0.0008142534353123032,
      "fisher_score": 0.08325953001607604,
      "auc_ovr": 0.5550666666666668,
      "n": 100
    },
    {
      "feature": "X35",
      "class": "频率失准",
      "mean": 0.0003036284668598801,
      "std": 4.2159071598822954e-05,
      "fisher_score": 0.2652269098942511,
      "auc_ovr": 0.1926,
      "n": 100
    },
    {
      "feature": "X35",
      "class": "参考电平失准",
      "mean": 0.0003262735870758733,
      "std": 1.012215141254654e-05,
      "fisher_score": 0.20496873162964788,
      "auc_ovr": 0.3194,
      "n": 100
    },
    {
      "feature": "X36",
      "class": "正常",
      "mean": 0.882482430614287,
      "std": 0.03125084257907663,
      "fisher_score": 0.04946419104299653,
      "auc_ovr": 0.5850666666666666,
      "n": 100
    },
    {
      "feature": "X36",
      "class": "幅度失准",
      "mean": 0.8547796332556782,
      "std": 0.16640054848105837,
      "fisher_score": 0.006803327141666489,
      "auc_ovr": 0.6839333333333333,
      "n": 100
    },
    {
      "feature": "X36",
      "class": "频率失准",
      "mean": 0.8669946030621412,
      "std": 0.027432684830268724,
      "fisher_score": 0.0005142994199385387,
      "auc_ovr": 0.42280000000000006,
      "n": 100
    },
    {
      "feature": "X36",
      "class": "参考电平失准",
      "mean": 0.8566942520887649,
      "std": 0.02462195818259273,
      "fisher_score": 0.012310375814063846,
      "auc_ovr": 0.3082,
      "n": 100
    },
    {
      "feature": "X37",
      "class": "正常",
      "mean": 0.053409951032385675,
      "std": 0.007691053677076466,
      "fisher_score": 1.2798381217783878,
      "auc_ovr": 0.9098333333333334,
      "n": 100
    },
    {
      "feature": "X37",
      "class": "幅度失准",
      "mean": 0.04717087150591736,
      "std": 0.016288899662189403,
      "fisher_score": 0.15719963164297407,
      "auc_ovr": 0.6772666666666666,
      "n": 100
    },
    {
      "feature": "X37",
      "class": "频率失准",
      "mean": 0.0323480199880211,
      "std": 0.003616781053307472,
      "fisher_score": 0.6989298520460175,
      "auc_ovr": 0.20263333333333333,
      "n": 100
    },
    {
      "feature": "X37",
      "class": "参考电平失准",
      "mean": 0.03221878041780988,
      "std": 0.0029680921821858696,
      "fisher_score": 0.7332926840424381,
      "auc_ovr": 0.21026666666666666,
      "n": 100
    },
    {
      "feature": "X4",
      "class": "正常",
      "mean": 0.0,
      "std": 0.0,
      "fisher_score": 0.0,
      "auc_ovr": 0.5,
      "n": 100
    },
    {
      "feature": "X4",
      "class": "幅度失准",
      "mean": 0.0,
      "std": 0.0,
      "fisher_score": 0.0,
      "auc_ovr": 0.5,
      "n": 100
    },
    {
      "feature": "X4",
      "class": "频率失准",
      "mean": 0.0,
      "std": 0.0,
      "fisher_score": 0.0,
      "auc_ovr": 0.5,
      "n": 100
    },
    {
      "feature": "X4",
      "class": "参考电平失准",
      "mean": 0.0,
      "std": 0.0,
      "fisher_score": 0.0,
      "auc_ovr": 0.5,
      "n": 100
    },
    {
      "feature": "X5",
      "class": "正常",
      "mean": 0.03268982310778868,
      "std": 0.004476670368751702,
      "fisher_score": 1.2348873728767564,
      "auc_ovr": 0.8733666666666667,
      "n": 100
    },
    {
      "feature": "X5",
      "class": "幅度失准",
      "mean": 0.03006245555003319,
      "std": 0.006221388382341179,
      "fisher_score": 0.25904765669718954,
      "auc_ovr": 0.7168333333333333,
      "n": 100
    },
    {
      "feature": "X5",
      "class": "频率失准",
      "mean": 0.02185758384172067,
      "std": 0.002326926771929522,
      "fisher_score": 0.9693771999737917,
      "auc_ovr": 0.1609,
      "n": 100
    },
    {
      "feature": "X5",
      "class": "参考电平失准",
      "mean": 0.022585905094786383,
      "std": 0.002093135341707631,
      "fisher_score": 0.6706171666753595,
      "auc_ovr": 0.2489,
      "n": 100
    },
    {
      "feature": "X6",
      "class": "正常",
      "mean": 0.003163770830542903,
      "std": 0.0009513284862119797,
      "fisher_score": 0.4476369963588937,
      "auc_ovr": 0.8487666666666667,
      "n": 100
    },
    {
      "feature": "X6",
      "class": "幅度失准",
      "mean": 0.003369212134250086,
      "std": 0.002106921514936878,
      "fisher_score": 0.4103700951909523,
      "auc_ovr": 0.7707666666666666,
      "n": 100
    },
    {
      "feature": "X6",
      "class": "频率失准",
      "mean": 0.0011898402771600347,
      "std": 0.00026113014667739147,
      "fisher_score": 0.6742919901772361,
      "auc_ovr": 0.18963333333333338,
      "n": 100
    },
    {
      "feature": "X6",
      "class": "参考电平失准",
      "mean": 0.0011860131619244436,
      "std": 0.0002308858776797695,
      "fisher_score": 0.6825133386802853,
      "auc_ovr": 0.19083333333333333,
      "n": 100
    },
    {
      "feature": "X7",
      "class": "正常",
      "mean": 0.132898288975304,
      "std": 0.02293779196506973,
      "fisher_score": 1.6072375426667143,
      "auc_ovr": 0.9137,
      "n": 100
    },
    {
      "feature": "X7",
      "class": "幅度失准",
      "mean": 0.10604732781479562,
      "std": 0.036875270326338014,
      "fisher_score": 0.03550452981944348,
      "auc_ovr": 0.5976,
      "n": 100
    },
    {
      "feature": "X7",
      "class": "频率失准",
      "mean": 0.07466386833818711,
      "std": 0.010989215188919666,
      "fisher_score": 0.8897051911212971,
      "auc_ovr": 0.14576666666666666,
      "n": 100
    },
    {
      "feature": "X7",
      "class": "参考电平失准",
      "mean": 0.08354713948273698,
      "std": 0.01288209177525513,
      "fisher_score": 0.3144122714808263,
      "auc_ovr": 0.3429333333333333,
      "n": 100
    },
    {
      "feature": "X8",
      "class": "正常",
      "mean": 0.044158588809634136,
      "std": 0.0064029983933608,
      "fisher_score": 0.6500098652130267,
      "auc_ovr": 0.8425333333333334,
      "n": 100
    },
    {
      "feature": "X8",
      "class": "幅度失准",
      "mean": 0.04521627900520811,
      "std": 0.014253592694879262,
      "fisher_score": 0.5386751422738354,
      "auc_ovr": 0.78,
      "n": 100
    },
    {
      "feature": "X8",
      "class": "频率失准",
      "mean": 0.027157359813607194,
      "std": 0.0028729864793976432,
      "fisher_score": 0.8452845461507118,
      "auc_ovr": 0.18866666666666662,
      "n": 100
    },
    {
      "feature": "X8",
      "class": "参考电平失准",
      "mean": 0.027080072802762346,
      "std": 0.0025361019045356684,
      "fisher_score": 0.8701255527660918,
      "auc_ovr": 0.18880000000000002,
      "n": 100
    },
    {
      "feature": "X9",
      "class": "正常",
      "mean": 0.002911774216132312,
      "std": 0.0008801730002265353,
      "fisher_score": 0.7380964916332737,
      "auc_ovr": 0.9098666666666667,
      "n": 100
    },
    {
      "feature": "X9",
      "class": "幅度失准",
      "mean": 0.0024903785779540567,
      "std": 0.00198292582597038,
      "fisher_score": 0.13393660388894416,
      "auc_ovr": 0.6771666666666668,
      "n": 100
    },
    {
      "feature": "X9",
      "class": "频率失准",
      "mean": 0.0010594646769733046,
      "std": 0.00024719095706012494,
      "fisher_score": 0.52098286033114,
      "auc_ovr": 0.20266666666666666,
      "n": 100
    },
    {
      "feature": "X9",
      "class": "参考电平失准",
      "mean": 0.0010468536015689385,
      "std": 0.00019482261752116613,
      "fisher_score": 0.543049520255931,
      "auc_ovr": 0.2103,
      "n": 100
    },
    {
      "feature": "band_offset_db_1",
      "class": "正常",
      "mean": 0.001293843731942328,
      "std": 0.040112977261011644,
      "fisher_score": 4.792158523117838e-06,
      "auc_ovr": 0.5478000000000001,
      "n": 100
    },
    {
      "feature": "band_offset_db_1",
      "class": "幅度失准",
      "mean": 0.010136842766392692,
      "std": 0.0494142952740662,
      "fisher_score": 0.04527334334516019,
      "auc_ovr": 0.5854000000000001,
      "n": 100
    },
    {
      "feature": "band_offset_db_1",
      "class": "频率失准",
      "mean": -0.0036984343725165658,
      "std": 0.01469855966121242,
      "fisher_score": 0.02564593922482874,
      "auc_ovr": 0.42373333333333335,
      "n": 100
    },
    {
      "feature": "band_offset_db_1",
      "class": "参考电平失准",
      "mean": -0.0028923540830681914,
      "std": 0.014926871131826787,
      "fisher_score": 0.017831612968620913,
      "auc_ovr": 0.4430666666666666,
      "n": 100
    },
    {
      "feature": "band_offset_db_2",
      "class": "正常",
      "mean": 0.0023300280844073917,
      "std": 0.01258211820476419,
      "fisher_score": 0.0009681692081776791,
      "auc_ovr": 0.5087333333333333,
      "n": 100
    },
    {
      "feature": "band_offset_db_2",
      "class": "幅度失准",
      "mean": 0.009847322969733572,
      "std": 0.02682434665068445,
      "fisher_score": 0.11094068882677952,
      "auc_ovr": 0.6598333333333334,
      "n": 100
    },
    {
      "feature": "band_offset_db_2",
      "class": "频率失准",
      "mean": -0.000542994077225476,
      "std": 0.0040620420520079414,
      "fisher_score": 0.05914326545948796,
      "auc_ovr": 0.40163333333333334,
      "n": 100
    },
    {
      "feature": "band_offset_db_2",
      "class": "参考电平失准",
      "mean": -0.00035789875023008123,
      "std": 0.006001308773468596,
      "fisher_score": 0.05078543846616603,
      "auc_ovr": 0.42980000000000007,
      "n": 100
    },
    {
      "feature": "band_offset_db_3",
      "class": "正常",
      "mean": -0.0015813374986570672,
      "std": 0.021969723204031295,
      "fisher_score": 0.0024211941929468453,
      "auc_ovr": 0.4899,
      "n": 100
    },
    {
      "feature": "band_offset_db_3",
      "class": "幅度失准",
      "mean": 0.002049651101437204,
      "std": 0.022387025518092935,
      "fisher_score": 0.018169544874961304,
      "auc_ovr": 0.5281,
      "n": 100
    },
    {
      "feature": "band_offset_db_3",
      "class": "频率失准",
      "mean": -0.0007363341448733695,
      "std": 0.005217031544225269,
      "fisher_score": 6.820024493998347e-05,
      "auc_ovr": 0.5159666666666667,
      "n": 100
    },
    {
      "feature": "band_offset_db_3",
      "class": "参考电平失准",
      "mean": -0.002193064659995194,
      "std": 0.008373123439745242,
      "fisher_score": 0.010806447590792233,
      "auc_ovr": 0.4660333333333334,
      "n": 100
    },
    {
      "feature": "band_offset_db_4",
      "class": "正常",
      "mean": -0.0018977035395983143,
      "std": 0.015537308121052144,
      "fisher_score": 0.021355543714151423,
      "auc_ovr": 0.5241,
      "n": 100
    },
    {
      "feature": "band_offset_db_4",
      "class": "幅度失准",
      "mean": -0.014615053491678348,
      "std": 0.022249808450470768,
      "fisher_score": 0.31837817357294484,
      "auc_ovr": 0.3249,
      "n": 100
    },
    {
      "feature": "band_offset_db_4",
      "class": "频率失准",
      "mean": -0.0005739272201730827,
      "std": 0.00499682653830477,
      "fisher_score": 0.07524581823763057,
      "auc_ovr": 0.5669000000000001,
      "n": 100
    },
    {
      "feature": "band_offset_db_4",
      "class": "参考电平失准",
      "mean": -3.201840280221191e-05,
      "std": 0.006001629438964852,
      "fisher_score": 0.09722821397957557,
      "auc_ovr": 0.5841000000000001,
      "n": 100
    },
    {
      "feature": "compress_ratio",
      "class": "正常",
      "mean": 0.19999999999999996,
      "std": 5.551115123125783e-17,
      "fisher_score": 0.02131842600135924,
      "auc_ovr": 0.515,
      "n": 100
    },
    {
      "feature": "compress_ratio",
      "class": "幅度失准",
      "mean": 0.19337804878048778,
      "std": 0.02562035494963701,
      "fisher_score": 0.0668037755616413,
      "auc_ovr": 0.455,
      "n": 100
    },
    {
      "feature": "compress_ratio",
      "class": "频率失准",
      "mean": 0.19999999999999996,
      "std": 5.551115123125783e-17,
      "fisher_score": 0.02131842600135924,
      "auc_ovr": 0.515,
      "n": 100
    },
    {
      "feature": "compress_ratio",
      "class": "参考电平失准",
      "mean": 0.19999999999999996,
      "std": 5.551115123125783e-17,
      "fisher_score": 0.02131842600135924,
      "auc_ovr": 0.515,
      "n": 100
    },
    {
      "feature": "compress_ratio_high",
      "class": "正常",
      "mean": 0.19999999999999996,
      "std": 5.551115123125783e-17,
      "fisher_score": 0.02451903034105421,
      "auc_ovr": 0.5166666666666667,
      "n": 100
    },
    {
      "feature": "compress_ratio_high",
      "class": "幅度失准",
      "mean": 0.19220338983050847,
      "std": 0.028033303951234375,
      "fisher_score": 0.07735039141076427,
      "auc_ovr": 0.45,
      "n": 100
    },
    {
      "feature": "compress_ratio_high",
      "class": "频率失准",
      "mean": 0.19999999999999996,
      "std": 5.551115123125783e-17,
      "fisher_score": 0.02451903034105421,
      "auc_ovr": 0.5166666666666667,
      "n": 100
    },
    {
      "feature": "compress_ratio_high",
      "class": "参考电平失准",
      "mean": 0.19999999999999996,
      "std": 5.551115123125783e-17,
      "fisher_score": 0.02451903034105421,
      "auc_ovr": 0.5166666666666667,
      "n": 100
    },
    {
      "feature": "env_overrun_max",
      "class": "正常",
      "mean": 0.04935712194880306,
      "std": 0.027738769191707296,
      "fisher_score": 1.4037027336274885,
      "auc_ovr": 0.9244666666666667,
      "n": 100
    },
    {
      "feature": "env_overrun_max",
      "class": "幅度失准",
      "mean": 0.02268986908471117,
      "std": 0.032613577782949404,
      "fisher_score": 0.020166121288264442,
      "auc_ovr": 0.5725666666666667,
      "n": 100
    },
    {
      "feature": "env_overrun_max",
      "class": "频率失准",
      "mean": 0.0002751382970802574,
      "std": 0.001422731663899284,
      "fisher_score": 0.5542191646966195,
      "auc_ovr": 0.2601333333333333,
      "n": 100
    },
    {
      "feature": "env_overrun_max",
      "class": "参考电平失准",
      "mean": 7.116297322248499e-05,
      "std": 0.0007080626434352737,
      "fisher_score": 0.5693603676519028,
      "auc_ovr": 0.24283333333333335,
      "n": 100
    },
    {
      "feature": "env_overrun_mean",
      "class": "正常",
      "mean": 0.001096966575910662,
      "std": 0.0014711215434154669,
      "fisher_score": 0.04788486442108793,
      "auc_ovr": 0.9113,
      "n": 100
    },
    {
      "feature": "env_overrun_mean",
      "class": "幅度失准",
      "mean": 0.0014046506524337293,
      "std": 0.004112129578398761,
      "fisher_score": 0.06023999772250967,
      "auc_ovr": 0.5851000000000001,
      "n": 100
    },
    {
      "feature": "env_overrun_mean",
      "class": "频率失准",
      "mean": 5.462096761756961e-07,
      "std": 2.997290741232738e-06,
      "fisher_score": 0.10341844148262994,
      "auc_ovr": 0.2597666666666667,
      "n": 100
    },
    {
      "feature": "env_overrun_mean",
      "class": "参考电平失准",
      "mean": 1.2929081018827858e-06,
      "std": 1.2864273187067373e-05,
      "fisher_score": 0.10316363539040758,
      "auc_ovr": 0.24383333333333335,
      "n": 100
    },
    {
      "feature": "env_overrun_rate",
      "class": "正常",
      "mean": 0.04680487804878049,
      "std": 0.04213261265783754,
      "fisher_score": 0.20277863687189882,
      "auc_ovr": 0.9065833333333333,
      "n": 100
    },
    {
      "feature": "env_overrun_rate",
      "class": "幅度失准",
      "mean": 0.044890243902439016,
      "std": 0.09066623244040495,
      "fisher_score": 0.09149842153326643,
      "auc_ovr": 0.58855,
      "n": 100
    },
    {
      "feature": "env_overrun_rate",
      "class": "频率失准",
      "mean": 0.0001097560975609756,
      "std": 0.0005201187344423445,
      "fisher_score": 0.2456628253415655,
      "auc_ovr": 0.26028333333333337,
      "n": 100
    },
    {
      "feature": "env_overrun_rate",
      "class": "参考电平失准",
      "mean": 0.00025609756097560977,
      "std": 0.0025481385584437827,
      "fisher_score": 0.24207994862034657,
      "auc_ovr": 0.24458333333333335,
      "n": 100
    },
    {
      "feature": "freq_shift_score",
      "class": "正常",
      "mean": 0.44171629718198735,
      "std": 0.12453467275676261,
      "fisher_score": 1.9978167492566345,
      "auc_ovr": 0.9172,
      "n": 100
    },
    {
      "feature": "freq_shift_score",
      "class": "幅度失准",
      "mean": 0.31961659675042015,
      "std": 0.15042682716592326,
      "fisher_score": 0.19756112579469656,
      "auc_ovr": 0.7016333333333333,
      "n": 100
    },
    {
      "feature": "freq_shift_score",
      "class": "频率失准",
      "mean": 0.09425210752359979,
      "std": 0.049145275618697866,
      "fisher_score": 1.074736469518697,
      "auc_ovr": 0.17103333333333334,
      "n": 100
    },
    {
      "feature": "freq_shift_score",
      "class": "参考电平失准",
      "mean": 0.107834618315324,
      "std": 0.06475448759229784,
      "fisher_score": 0.8186537713504536,
      "auc_ovr": 0.21013333333333337,
      "n": 100
    },
    {
      "feature": "global_offset_db",
      "class": "正常",
      "mean": -8.881784197001253e-18,
      "std": 1.5358040586646547e-16,
      "fisher_score": 1.2621774483536189e-24,
      "auc_ovr": 0.5201666666666667,
      "n": 100
    },
    {
      "feature": "global_offset_db",
      "class": "幅度失准",
      "mean": -8.881784197001253e-18,
      "std": 3.8704610306973784e-16,
      "fisher_score": 1.2621774483536189e-24,
      "auc_ovr": 0.5180333333333333,
      "n": 100
    },
    {
      "feature": "global_offset_db",
      "class": "频率失准",
      "mean": -3.552713678800501e-17,
      "std": 4.514882699573816e-16,
      "fisher_score": 0.0,
      "auc_ovr": 0.49879999999999997,
      "n": 100
    },
    {
      "feature": "global_offset_db",
      "class": "参考电平失准",
      "mean": -8.881784197001253e-17,
      "std": 3.871479975306501e-16,
      "fisher_score": 5.0487097934144756e-24,
      "auc_ovr": 0.463,
      "n": 100
    },
    {
      "feature": "high_low_energy_ratio",
      "class": "正常",
      "mean": 2.484111348252073,
      "std": 3.3602059231296364,
      "fisher_score": 0.019649279002946326,
      "auc_ovr": 0.3943333333333333,
      "n": 100
    },
    {
      "feature": "high_low_energy_ratio",
      "class": "幅度失准",
      "mean": 2.59074306388551,
      "std": 5.694980924974807,
      "fisher_score": 0.019373799736137606,
      "auc_ovr": 0.34376666666666666,
      "n": 100
    },
    {
      "feature": "high_low_energy_ratio",
      "class": "频率失准",
      "mean": 18.266559807618634,
      "std": 42.82063755563579,
      "fisher_score": 1.429992530245379e-06,
      "auc_ovr": 0.5990666666666667,
      "n": 100
    },
    {
      "feature": "high_low_energy_ratio",
      "class": "参考电平失准",
      "mean": 50.28364660811405,
      "std": 256.3765538128643,
      "fisher_score": 0.027202653119956358,
      "auc_ovr": 0.6628333333333334,
      "n": 100
    },
    {
      "feature": "mod_[RF板][Mixer1]",
      "class": "正常",
      "mean": 0.018101187450187593,
      "std": 0.019209572602338295,
      "fisher_score": 0.002588099357247047,
      "auc_ovr": 0.4955833333333333,
      "n": 100
    },
    {
      "feature": "mod_[RF板][Mixer1]",
      "class": "幅度失准",
      "mean": 0.013565910845596751,
      "std": 0.013501387137268306,
      "fisher_score": 0.0771084404448044,
      "auc_ovr": 0.4577333333333333,
      "n": 100
    },
    {
      "feature": "mod_[RF板][Mixer1]",
      "class": "频率失准",
      "mean": 0.03619645314439634,
      "std": 0.030379970309522334,
      "fisher_score": 0.45668368637543083,
      "auc_ovr": 0.7049833333333334,
      "n": 100
    },
    {
      "feature": "mod_[RF板][Mixer1]",
      "class": "参考电平失准",
      "mean": 0.009064443944136589,
      "std": 1.7860071305544553e-18,
      "fisher_score": 0.3130999715657724,
      "auc_ovr": 0.3417,
      "n": 100
    },
    {
      "feature": "mod_[RF板][Mixer2]",
      "class": "正常",
      "mean": 0.0,
      "std": 0.0,
      "fisher_score": 0.0,
      "auc_ovr": 0.5,
      "n": 100
    },
    {
      "feature": "mod_[RF板][Mixer2]",
      "class": "幅度失准",
      "mean": 0.0,
      "std": 0.0,
      "fisher_score": 0.0,
      "auc_ovr": 0.5,
      "n": 100
    },
    {
      "feature": "mod_[RF板][Mixer2]",
      "class": "频率失准",
      "mean": 0.0,
      "std": 0.0,
      "fisher_score": 0.0,
      "auc_ovr": 0.5,
      "n": 100
    },
    {
      "feature": "mod_[RF板][Mixer2]",
      "class": "参考电平失准",
      "mean": 0.0,
      "std": 0.0,
      "fisher_score": 0.0,
      "auc_ovr": 0.5,
      "n": 100
    },
    {
      "feature": "mod_[RF板][RF] 低频通路固定滤波/抑制网络",
      "class": "正常",
      "mean": 0.017804446672315673,
      "std": 0.018894661576070455,
      "fisher_score": 0.002588099258212416,
      "auc_ovr": 0.5081166666666667,
      "n": 100
    },
    {
      "feature": "mod_[RF板][RF] 低频通路固定滤波/抑制网络",
      "class": "幅度失准",
      "mean": 0.0133435188645214,
      "std": 0.013280052921903256,
      "fisher_score": 0.07710843694339747,
      "auc_ovr": 0.4629666666666667,
      "n": 100
    },
    {
      "feature": "mod_[RF板][RF] 低频通路固定滤波/抑制网络",
      "class": "频率失准",
      "mean": 0.03560306866661936,
      "std": 0.029881938009366227,
      "fisher_score": 0.45668367267429455,
      "auc_ovr": 0.7113666666666667,
      "n": 100
    },
    {
      "feature": "mod_[RF板][RF] 低频通路固定滤波/抑制网络",
      "class": "参考电平失准",
      "mean": 0.008915846502429428,
      "std": 2.0452088152474867e-18,
      "fisher_score": 0.3130999536375031,
      "auc_ovr": 0.31755,
      "n": 100
    },
    {
      "feature": "mod_[RF板][RF] 步进衰减器/ATT",
      "class": "正常",
      "mean": 0.0,
      "std": 0.0,
      "fisher_score": 0.0,
      "auc_ovr": 0.5,
      "n": 100
    },
    {
      "feature": "mod_[RF板][RF] 步进衰减器/ATT",
      "class": "幅度失准",
      "mean": 0.0,
      "std": 0.0,
      "fisher_score": 0.0,
      "auc_ovr": 0.5,
      "n": 100
    },
    {
      "feature": "mod_[RF板][RF] 步进衰减器/ATT",
      "class": "频率失准",
      "mean": 0.0,
      "std": 0.0,
      "fisher_score": 0.0,
      "auc_ovr": 0.5,
      "n": 100
    },
    {
      "feature": "mod_[RF板][RF] 步进衰减器/ATT",
      "class": "参考电平失准",
      "mean": 0.0,
      "std": 0.0,
      "fisher_score": 0.0,
      "auc_ovr": 0.5,
      "n": 100
    },
    {
      "feature": "mod_[RF板][RF] 输入连接/匹配/保护",
      "class": "正常",
      "mean": 0.32153357322531645,
      "std": 0.01260368705098363,
      "fisher_score": 0.002588095459196823,
      "auc_ovr": 0.4884333333333334,
      "n": 100
    },
    {
      "feature": "mod_[RF板][RF] 输入连接/匹配/保护",
      "class": "幅度失准",
      "mean": 0.32450923583880703,
      "std": 0.008858461442894974,
      "fisher_score": 0.07710830262775496,
      "auc_ovr": 0.55415,
      "n": 100
    },
    {
      "feature": "mod_[RF板][RF] 输入连接/匹配/保护",
      "class": "频率失准",
      "mean": 0.309660999554081,
      "std": 0.01993275156745471,
      "fisher_score": 0.4566831470918338,
      "auc_ovr": 0.3058333333333333,
      "n": 100
    },
    {
      "feature": "mod_[RF板][RF] 输入连接/匹配/保护",
      "class": "参考电平失准",
      "mean": 0.3274627154018796,
      "std": 2.419674984566563e-17,
      "fisher_score": 0.31309926590082726,
      "auc_ovr": 0.6515833333333333,
      "n": 100
    },
    {
      "feature": "mod_[RF板][YTF]",
      "class": "正常",
      "mean": 0.0,
      "std": 0.0,
      "fisher_score": 0.0,
      "auc_ovr": 0.5,
      "n": 100
    },
    {
      "feature": "mod_[RF板][YTF]",
      "class": "幅度失准",
      "mean": 0.0,
      "std": 0.0,
      "fisher_score": 0.0,
      "auc_ovr": 0.5,
      "n": 100
    },
    {
      "feature": "mod_[RF板][YTF]",
      "class": "频率失准",
      "mean": 0.0,
      "std": 0.0,
      "fisher_score": 0.0,
      "auc_ovr": 0.5,
      "n": 100
    },
    {
      "feature": "mod_[RF板][YTF]",
      "class": "参考电平失准",
      "mean": 0.0,
      "std": 0.0,
      "fisher_score": 0.0,
      "auc_ovr": 0.5,
      "n": 100
    },
    {
      "feature": "mod_[数字中频板][ADC]",
      "class": "正常",
      "mean": 0.07399139695248849,
      "std": 0.007673306946429907,
      "fisher_score": 0.002588083837760369,
      "auc_ovr": 0.49483333333333346,
      "n": 100
    },
    {
      "feature": "mod_[数字中频板][ADC]",
      "class": "幅度失准",
      "mean": 0.07580302338449728,
      "std": 0.00539315943417864,
      "fisher_score": 0.0771078917478669,
      "auc_ovr": 0.5494333333333333,
      "n": 100
    },
    {
      "feature": "mod_[数字中频板][ADC]",
      "class": "频率失准",
      "mean": 0.06676320240473654,
      "std": 0.012135347414237422,
      "fisher_score": 0.45668153929860117,
      "auc_ovr": 0.26991666666666664,
      "n": 100
    },
    {
      "feature": "mod_[数字中频板][ADC]",
      "class": "参考电平失准",
      "mean": 0.07760114445460864,
      "std": 1.1102230246251566e-17,
      "fisher_score": 0.3130971620755422,
      "auc_ovr": 0.6858166666666666,
      "n": 100
    },
    {
      "feature": "mod_[数字中频板][RBW]",
      "class": "正常",
      "mean": 0.06829975103306628,
      "std": 0.007083052565935295,
      "fisher_score": 0.0025880806318888503,
      "auc_ovr": 0.475,
      "n": 100
    },
    {
      "feature": "mod_[数字中频板][RBW]",
      "class": "幅度失准",
      "mean": 0.06997202158568978,
      "std": 0.004978301016164898,
      "fisher_score": 0.07710777840330196,
      "auc_ovr": 0.5951666666666666,
      "n": 100
    },
    {
      "feature": "mod_[数字中频板][RBW]",
      "class": "频率失准",
      "mean": 0.06162757145052604,
      "std": 0.011201859151603771,
      "fisher_score": 0.45668109577472055,
      "auc_ovr": 0.30248333333333327,
      "n": 100
    },
    {
      "feature": "mod_[数字中频板][RBW]",
      "class": "参考电平失准",
      "mean": 0.07163182565040796,
      "std": 2.0014830212433607e-17,
      "fisher_score": 0.31309658171923155,
      "auc_ovr": 0.62735,
      "n": 100
    },
    {
      "feature": "mod_[数字中频板][VBW]",
      "class": "正常",
      "mean": 0.05691645919422192,
      "std": 0.005902543804946081,
      "fisher_score": 0.002588071096392134,
      "auc_ovr": 0.4878,
      "n": 100
    },
    {
      "feature": "mod_[数字中频板][VBW]",
      "class": "幅度失准",
      "mean": 0.058310017988074836,
      "std": 0.004148584180137415,
      "fisher_score": 0.07710744127320297,
      "auc_ovr": 0.5699166666666666,
      "n": 100
    },
    {
      "feature": "mod_[数字中频板][VBW]",
      "class": "频率失准",
      "mean": 0.05135630954210504,
      "std": 0.009334882626336473,
      "fisher_score": 0.4566797765623833,
      "auc_ovr": 0.29346666666666665,
      "n": 100
    },
    {
      "feature": "mod_[数字中频板][VBW]",
      "class": "参考电平失准",
      "mean": 0.05969318804200666,
      "std": 1.4338515319353585e-17,
      "fisher_score": 0.31309485552014404,
      "auc_ovr": 0.6488166666666666,
      "n": 100
    },
    {
      "feature": "mod_[数字中频板][检波/对数]",
      "class": "正常",
      "mean": 0.07968304287191068,
      "std": 0.008263561326924513,
      "fisher_score": 0.0025880863815268317,
      "auc_ovr": 0.4791333333333333,
      "n": 100
    },
    {
      "feature": "mod_[数字中频板][检波/对数]",
      "class": "幅度失准",
      "mean": 0.08163402518330477,
      "std": 0.005808017852192381,
      "fisher_score": 0.07710798168354542,
      "auc_ovr": 0.6005333333333333,
      "n": 100
    },
    {
      "feature": "mod_[数字中频板][检波/对数]",
      "class": "频率失准",
      "mean": 0.07189883335894703,
      "std": 0.013068835676871065,
      "fisher_score": 0.45668189122183794,
      "auc_ovr": 0.29296666666666665,
      "n": 100
    },
    {
      "feature": "mod_[数字中频板][检波/对数]",
      "class": "参考电平失准",
      "mean": 0.08357046325880929,
      "std": 1.9577028858666475e-17,
      "fisher_score": 0.31309762257203844,
      "auc_ovr": 0.6273666666666667,
      "n": 100
    },
    {
      "feature": "mod_[时钟板][参考分配]",
      "class": "正常",
      "mean": 0.014540298115724463,
      "std": 0.015430640287124202,
      "fisher_score": 0.0025880977373568793,
      "auc_ovr": 0.5110666666666667,
      "n": 100
    },
    {
      "feature": "mod_[时钟板][参考分配]",
      "class": "幅度失准",
      "mean": 0.010897207072692478,
      "std": 0.010845376552887656,
      "fisher_score": 0.07710838317295805,
      "auc_ovr": 0.46088333333333337,
      "n": 100
    },
    {
      "feature": "mod_[时钟板][参考分配]",
      "class": "频率失准",
      "mean": 0.029075839411072474,
      "std": 0.024403582707649082,
      "fisher_score": 0.4566834622684978,
      "auc_ovr": 0.7214166666666667,
      "n": 100
    },
    {
      "feature": "mod_[时钟板][参考分配]",
      "class": "参考电平失准",
      "mean": 0.007281274643650701,
      "std": 9.096966653664784e-19,
      "fisher_score": 0.3130996783165324,
      "auc_ovr": 0.3066333333333333,
      "n": 100
    },
    {
      "feature": "mod_[时钟板][参考域] 10MHz基准",
      "class": "正常",
      "mean": 0.014540298115724463,
      "std": 0.015430640287124202,
      "fisher_score": 0.0025880977373568793,
      "auc_ovr": 0.5110666666666667,
      "n": 100
    },
    {
      "feature": "mod_[时钟板][参考域] 10MHz基准",
      "class": "幅度失准",
      "mean": 0.010897207072692478,
      "std": 0.010845376552887656,
      "fisher_score": 0.07710838317295805,
      "auc_ovr": 0.46088333333333337,
      "n": 100
    },
    {
      "feature": "mod_[时钟板][参考域] 10MHz基准",
      "class": "频率失准",
      "mean": 0.029075839411072474,
      "std": 0.024403582707649082,
      "fisher_score": 0.4566834622684978,
      "auc_ovr": 0.7214166666666667,
      "n": 100
    },
    {
      "feature": "mod_[时钟板][参考域] 10MHz基准",
      "class": "参考电平失准",
      "mean": 0.007281274643650701,
      "std": 9.096966653664784e-19,
      "fisher_score": 0.3130996783165324,
      "auc_ovr": 0.3066333333333333,
      "n": 100
    },
    {
      "feature": "mod_[校准链路][校准源]",
      "class": "正常",
      "mean": 0.028369013113671477,
      "std": 0.0029420196719393806,
      "fisher_score": 0.002587976692571789,
      "auc_ovr": 0.48455000000000004,
      "n": 100
    },
    {
      "feature": "mod_[校准链路][校准源]",
      "class": "幅度失准",
      "mean": 0.029063608108813047,
      "std": 0.0020677891892023448,
      "fisher_score": 0.07710410362536192,
      "auc_ovr": 0.5563,
      "n": 100
    },
    {
      "feature": "mod_[校准链路][校准源]",
      "class": "频率失准",
      "mean": 0.02559765381571127,
      "std": 0.004652808895533125,
      "fisher_score": 0.45666671591486935,
      "auc_ovr": 0.29073333333333334,
      "n": 100
    },
    {
      "feature": "mod_[校准链路][校准源]",
      "class": "参考电平失准",
      "mean": 0.02975302501833178,
      "std": 5.742956581555481e-18,
      "fisher_score": 0.31307776605527426,
      "auc_ovr": 0.6684166666666667,
      "n": 100
    },
    {
      "feature": "mod_[校准链路][校准表/存储]",
      "class": "正常",
      "mean": 0.021276759835253612,
      "std": 0.0022065147539545352,
      "fisher_score": 0.002587879003430783,
      "auc_ovr": 0.5124666666666666,
      "n": 100
    },
    {
      "feature": "mod_[校准链路][校准表/存储]",
      "class": "幅度失准",
      "mean": 0.021797706081609785,
      "std": 0.0015508418919017585,
      "fisher_score": 0.07710064987281817,
      "auc_ovr": 0.5402499999999999,
      "n": 100
    },
    {
      "feature": "mod_[校准链路][校准表/存储]",
      "class": "频率失准",
      "mean": 0.019198240361783456,
      "std": 0.003489606671649842,
      "fisher_score": 0.45665320053072006,
      "auc_ovr": 0.28745,
      "n": 100
    },
    {
      "feature": "mod_[校准链路][校准表/存储]",
      "class": "参考电平失准",
      "mean": 0.022314768763748837,
      "std": 2.6193750069204537e-18,
      "fisher_score": 0.31306008251619444,
      "auc_ovr": 0.6598333333333333,
      "n": 100
    },
    {
      "feature": "mod_[校准链路][校准路径开关/耦合]",
      "class": "正常",
      "mean": 0.056738026227342954,
      "std": 0.005884039343878761,
      "fisher_score": 0.0025880708998002864,
      "auc_ovr": 0.48455000000000004,
      "n": 100
    },
    {
      "feature": "mod_[校准链路][校准路径开关/耦合]",
      "class": "幅度失准",
      "mean": 0.05812721621762609,
      "std": 0.0041355783784046895,
      "fisher_score": 0.07710743432265971,
      "auc_ovr": 0.5563,
      "n": 100
    },
    {
      "feature": "mod_[校准链路][校准路径开关/耦合]",
      "class": "频率失准",
      "mean": 0.05119530763142254,
      "std": 0.00930561779106625,
      "fisher_score": 0.45667974936441746,
      "auc_ovr": 0.29073333333333334,
      "n": 100
    },
    {
      "feature": "mod_[校准链路][校准路径开关/耦合]",
      "class": "参考电平失准",
      "mean": 0.05950605003666356,
      "std": 1.1485913163110962e-17,
      "fisher_score": 0.3130948199314919,
      "auc_ovr": 0.6684166666666667,
      "n": 100
    },
    {
      "feature": "mod_中频放大器",
      "class": "正常",
      "mean": 0.11952456430786601,
      "std": 0.012395341990386775,
      "fisher_score": 0.002588095227173411,
      "auc_ovr": 0.46675,
      "n": 100
    },
    {
      "feature": "mod_中频放大器",
      "class": "幅度失准",
      "mean": 0.12245103777495712,
      "std": 0.008712026778288575,
      "fisher_score": 0.07710829442447101,
      "auc_ovr": 0.5756,
      "n": 100
    },
    {
      "feature": "mod_中频放大器",
      "class": "频率失准",
      "mean": 0.10784825003842057,
      "std": 0.019603253515306604,
      "fisher_score": 0.45668311499203856,
      "auc_ovr": 0.27725,
      "n": 100
    },
    {
      "feature": "mod_中频放大器",
      "class": "参考电平失准",
      "mean": 0.12535569488821394,
      "std": 3.7751664318895324e-17,
      "fisher_score": 0.31309922389756184,
      "auc_ovr": 0.6804,
      "n": 100
    },
    {
      "feature": "mod_前置放大器",
      "class": "正常",
      "mean": 0.0,
      "std": 0.0,
      "fisher_score": 0.0,
      "auc_ovr": 0.5,
      "n": 100
    },
    {
      "feature": "mod_前置放大器",
      "class": "幅度失准",
      "mean": 0.0,
      "std": 0.0,
      "fisher_score": 0.0,
      "auc_ovr": 0.5,
      "n": 100
    },
    {
      "feature": "mod_前置放大器",
      "class": "频率失准",
      "mean": 0.0,
      "std": 0.0,
      "fisher_score": 0.0,
      "auc_ovr": 0.5,
      "n": 100
    },
    {
      "feature": "mod_前置放大器",
      "class": "参考电平失准",
      "mean": 0.0,
      "std": 0.0,
      "fisher_score": 0.0,
      "auc_ovr": 0.5,
      "n": 100
    },
    {
      "feature": "mod_数字放大器",
      "class": "正常",
      "mean": 0.10244962654959944,
      "std": 0.010624578848902945,
      "fisher_score": 0.002588092671758189,
      "auc_ovr": 0.46541666666666665,
      "n": 100
    },
    {
      "feature": "mod_数字放大器",
      "class": "幅度失准",
      "mean": 0.10495803237853467,
      "std": 0.007467451524247348,
      "fisher_score": 0.0771082040768321,
      "auc_ovr": 0.5159166666666667,
      "n": 100
    },
    {
      "feature": "mod_数字放大器",
      "class": "频率失准",
      "mean": 0.09244135717578902,
      "std": 0.01680278872740566,
      "fisher_score": 0.45668276145775344,
      "auc_ovr": 0.30355,
      "n": 100
    },
    {
      "feature": "mod_数字放大器",
      "class": "参考电平失准",
      "mean": 0.10744773847561198,
      "std": 1.7053311162424517e-17,
      "fisher_score": 0.31309876129073216,
      "auc_ovr": 0.7151166666666667,
      "n": 100
    },
    {
      "feature": "mod_本振源(谐波发生器)",
      "class": "正常",
      "mean": 0.006231556335310486,
      "std": 0.006613131551624659,
      "fisher_score": 0.002588077442541421,
      "auc_ovr": 0.5089166666666668,
      "n": 100
    },
    {
      "feature": "mod_本振源(谐波发生器)",
      "class": "幅度失准",
      "mean": 0.004670231602582489,
      "std": 0.004648018522666138,
      "fisher_score": 0.0771076656429967,
      "auc_ovr": 0.4414666666666667,
      "n": 100
    },
    {
      "feature": "mod_本振源(谐波发生器)",
      "class": "频率失准",
      "mean": 0.012461074033316775,
      "std": 0.01045867830327818,
      "fisher_score": 0.45668065453663703,
      "auc_ovr": 0.73565,
      "n": 100
    },
    {
      "feature": "mod_本振源(谐波发生器)",
      "class": "参考电平失准",
      "mean": 0.0031205462758503,
      "std": 2.876713442418084e-19,
      "fisher_score": 0.31309600435493046,
      "auc_ovr": 0.3139666666666667,
      "n": 100
    },
    {
      "feature": "offset_db",
      "class": "正常",
      "mean": 0.002999999999999714,
      "std": 0.016896745248715664,
      "fisher_score": 0.42424397121655105,
      "auc_ovr": 0.3774666666666667,
      "n": 100
    },
    {
      "feature": "offset_db",
      "class": "幅度失准",
      "mean": 0.0009065898585383448,
      "std": 0.0032303191438661522,
      "fisher_score": 0.5375937669513146,
      "auc_ovr": 0.18753333333333333,
      "n": 100
    },
    {
      "feature": "offset_db",
      "class": "频率失准",
      "mean": 0.003854117895905551,
      "std": 0.002560279946348806,
      "fisher_score": 0.4212552682989015,
      "auc_ovr": 0.435,
      "n": 100
    },
    {
      "feature": "offset_db",
      "class": "参考电平失准",
      "mean": 0.1096667957281857,
      "std": 0.013480571215811603,
      "fisher_score": 40.360797851277276,
      "auc_ovr": 1.0,
      "n": 100
    },
    {
      "feature": "offset_slope",
      "class": "正常",
      "mean": -0.0003929280596006854,
      "std": 0.00458772433168828,
      "fisher_score": 0.03827876118153027,
      "auc_ovr": 0.5187333333333334,
      "n": 100
    },
    {
      "feature": "offset_slope",
      "class": "幅度失准",
      "mean": -0.005093535789298122,
      "std": 0.008052046053194019,
      "fisher_score": 0.3236848004203312,
      "auc_ovr": 0.3178333333333333,
      "n": 100
    },
    {
      "feature": "offset_slope",
      "class": "频率失准",
      "mean": -4.4832971927777105e-05,
      "std": 0.0016205603030721532,
      "fisher_score": 0.09141659351663703,
      "auc_ovr": 0.5911000000000001,
      "n": 100
    },
    {
      "feature": "offset_slope",
      "class": "参考电平失准",
      "mean": -0.000190401311404354,
      "std": 0.0016881782420167717,
      "fisher_score": 0.07259706140222792,
      "auc_ovr": 0.5723333333333334,
      "n": 100
    },
    {
      "feature": "ripple_hp",
      "class": "正常",
      "mean": 0.019400485237679198,
      "std": 0.001700814415827883,
      "fisher_score": 1.6591243423401825,
      "auc_ovr": 0.9324,
      "n": 100
    },
    {
      "feature": "ripple_hp",
      "class": "幅度失准",
      "mean": 0.012289530449469453,
      "std": 0.014622225915560007,
      "fisher_score": 0.027946920004089153,
      "auc_ovr": 0.47656666666666664,
      "n": 100
    },
    {
      "feature": "ripple_hp",
      "class": "频率失准",
      "mean": 0.005607952047473278,
      "std": 0.0021945467931682792,
      "fisher_score": 0.32185378354620536,
      "auc_ovr": 0.4096333333333333,
      "n": 100
    },
    {
      "feature": "ripple_hp",
      "class": "参考电平失准",
      "mean": 0.0036834338795004957,
      "std": 0.0011494253044919765,
      "fisher_score": 0.7162300339496422,
      "auc_ovr": 0.1814,
      "n": 100
    },
    {
      "feature": "shape_rmse",
      "class": "正常",
      "mean": 0.046517567804312085,
      "std": 0.007294193014788269,
      "fisher_score": 1.335958420782965,
      "auc_ovr": 0.8771666666666667,
      "n": 100
    },
    {
      "feature": "shape_rmse",
      "class": "幅度失准",
      "mean": 0.04239267200134646,
      "std": 0.019989139371787815,
      "fisher_score": 0.4260246306349566,
      "auc_ovr": 0.7491333333333333,
      "n": 100
    },
    {
      "feature": "shape_rmse",
      "class": "频率失准",
      "mean": 0.01503427225327204,
      "std": 0.00535276828219903,
      "fisher_score": 1.0430215867891401,
      "auc_ovr": 0.17240000000000003,
      "n": 100
    },
    {
      "feature": "shape_rmse",
      "class": "参考电平失准",
      "mean": 0.015621174334959728,
      "std": 0.005214643838485613,
      "fisher_score": 0.9455942474976473,
      "auc_ovr": 0.2013,
      "n": 100
    },
    {
      "feature": "switch_step_mean_abs",
      "class": "正常",
      "mean": 0.0,
      "std": 0.0,
      "fisher_score": 0.0,
      "auc_ovr": 0.5,
      "n": 100
    },
    {
      "feature": "switch_step_mean_abs",
      "class": "幅度失准",
      "mean": 0.0,
      "std": 0.0,
      "fisher_score": 0.0,
      "auc_ovr": 0.5,
      "n": 100
    },
    {
      "feature": "switch_step_mean_abs",
      "class": "频率失准",
      "mean": 0.0,
      "std": 0.0,
      "fisher_score": 0.0,
      "auc_ovr": 0.5,
      "n": 100
    },
    {
      "feature": "switch_step_mean_abs",
      "class": "参考电平失准",
      "mean": 0.0,
      "std": 0.0,
      "fisher_score": 0.0,
      "auc_ovr": 0.5,
      "n": 100
    },
    {
      "feature": "switch_step_std",
      "class": "正常",
      "mean": 0.0,
      "std": 0.0,
      "fisher_score": 0.0,
      "auc_ovr": 0.5,
      "n": 100
    },
    {
      "feature": "switch_step_std",
      "class": "幅度失准",
      "mean": 0.0,
      "std": 0.0,
      "fisher_score": 0.0,
      "auc_ovr": 0.5,
      "n": 100
    },
    {
      "feature": "switch_step_std",
      "class": "频率失准",
      "mean": 0.0,
      "std": 0.0,
      "fisher_score": 0.0,
      "auc_ovr": 0.5,
      "n": 100
    },
    {
      "feature": "switch_step_std",
      "class": "参考电平失准",
      "mean": 0.0,
      "std": 0.0,
      "fisher_score": 0.0,
      "auc_ovr": 0.5,
      "n": 100
    },
    {
      "feature": "tail_asym",
      "class": "正常",
      "mean": -0.009744108898420603,
      "std": 0.02650092510093135,
      "fisher_score": 0.03615390228118954,
      "auc_ovr": 0.5862,
      "n": 100
    },
    {
      "feature": "tail_asym",
      "class": "幅度失准",
      "mean": -0.011364120894480318,
      "std": 0.03298152815678151,
      "fisher_score": 0.013463959309618145,
      "auc_ovr": 0.6708333333333333,
      "n": 100
    },
    {
      "feature": "tail_asym",
      "class": "频率失准",
      "mean": -0.01995402696297272,
      "std": 0.013915032647948673,
      "fisher_score": 0.05640497843439507,
      "auc_ovr": 0.35096666666666665,
      "n": 100
    },
    {
      "feature": "tail_asym",
      "class": "参考电平失准",
      "mean": -0.017751269137474598,
      "std": 0.01414147413614315,
      "fisher_score": 0.018739415780517445,
      "auc_ovr": 0.392,
      "n": 100
    },
    {
      "feature": "viol_energy_aligned",
      "class": "正常",
      "mean": 0.001096966575910662,
      "std": 0.0014711215434154669,
      "fisher_score": 0.04788486442108793,
      "auc_ovr": 0.9113,
      "n": 100
    },
    {
      "feature": "viol_energy_aligned",
      "class": "幅度失准",
      "mean": 0.0014046506524337293,
      "std": 0.004112129578398761,
      "fisher_score": 0.06023999772250967,
      "auc_ovr": 0.5851000000000001,
      "n": 100
    },
    {
      "feature": "viol_energy_aligned",
      "class": "频率失准",
      "mean": 5.462096761756961e-07,
      "std": 2.997290741232738e-06,
      "fisher_score": 0.10341844148262994,
      "auc_ovr": 0.2597666666666667,
      "n": 100
    },
    {
      "feature": "viol_energy_aligned",
      "class": "参考电平失准",
      "mean": 1.2929081018827858e-06,
      "std": 1.2864273187067373e-05,
      "fisher_score": 0.10316363539040758,
      "auc_ovr": 0.24383333333333335,
      "n": 100
    },
    {
      "feature": "viol_rate_aligned",
      "class": "正常",
      "mean": 0.04680487804878049,
      "std": 0.04213261265783754,
      "fisher_score": 0.20277863687189882,
      "auc_ovr": 0.9065833333333333,
      "n": 100
    },
    {
      "feature": "viol_rate_aligned",
      "class": "幅度失准",
      "mean": 0.044890243902439016,
      "std": 0.09066623244040495,
      "fisher_score": 0.09149842153326643,
      "auc_ovr": 0.58855,
      "n": 100
    },
    {
      "feature": "viol_rate_aligned",
      "class": "频率失准",
      "mean": 0.0001097560975609756,
      "std": 0.0005201187344423445,
      "fisher_score": 0.2456628253415655,
      "auc_ovr": 0.26028333333333337,
      "n": 100
    },
    {
      "feature": "viol_rate_aligned",
      "class": "参考电平失准",
      "mean": 0.00025609756097560977,
      "std": 0.0025481385584437827,
      "fisher_score": 0.24207994862034657,
      "auc_ovr": 0.24458333333333335,
      "n": 100
    }
  ]
}